pytest_assurka/__init__.py
pytest_assurka/plugin.py
pytest_assurka-0.2.6.dist-info/entry_points.txt
pytest_assurka-0.2.6.dist-info/WHEEL
pytest_assurka-0.2.6.dist-info/METADATA
pytest_assurka-0.2.6.dist-info/RECORD
