Metadata-Version: 2.1
Name: pytest-assurka
Version: 0.2.6
Summary: A pytest plugin for Assurka Studio
Home-page: https://github.com/assurka-io/pytest-assurka
Keywords: testing,development,pytest,assurka,assurka_io
Author: Assurka Limited
Requires-Python: >=3.7,<4.0
Classifier: Framework :: Pytest
Classifier: Intended Audience :: Developers
Classifier: Programming Language :: Python :: 3
Classifier: Programming Language :: Python :: 3.10
Classifier: Programming Language :: Python :: 3.6
Classifier: Programming Language :: Python :: 3.7
Classifier: Programming Language :: Python :: 3.8
Classifier: Programming Language :: Python :: 3.9
Requires-Dist: requests (>=2.24.0,<3.0.0)
Project-URL: Homepage, https://www.assurka.io
Project-URL: Repository, https://github.com/assurka-io/pytest-assurka
Project-URL: Studio, https://studio.assurka.io
